{"name":"Canvas Open Action","title":"Canvas Open Action","description":"Kumpulan Desain & Koleksi Canvas Web3 Pixel & AI-Generated Streetwear dengan sistem enkripsi on-chain.","authors":["hey@funtend.xyz"],"initializeCalldataABI":"[{\"components\":[{\"type\":\"uint256[]\",\"name\":\"prices\"},{\"type\":\"uint256[]\",\"name\":\"communityIds\"},{\"type\":\"address[]\",\"name\":\"acceptedTokens\"},{\"type\":\"string\",\"name\":\"uri\"},{\"type\":\"address\",\"name\":\"fulfiller\"},{\"type\":\"uint256\",\"name\":\"amount\"},{\"type\":\"uint256\",\"name\":\"dropId\"},{\"type\":\"bool\",\"name\":\"unlimited\"},{\"type\":\"bool\",\"name\":\"encrypted\"}],\"type\":\"tuple\",\"name\":\"collectionValuesParams\"},{\"type\":\"uint8\",\"name\":\"pixelType\"}]","processCalldataABI":"[{\"type\":\"uint256[]\",\"name\":\"chosenIndexes\"},{\"type\":\"uint256[]\",\"name\":\"quantities\"},{\"type\":\"string\",\"name\":\"encryptedFulfillment\"},{\"type\":\"address\",\"name\":\"currency\"},{\"type\":\"bool\",\"name\":\"fiat\"}]","attributes":[{"key":"Category","type":"STRING","value":"Web3 Streetwear"}],"$schema":"https://json-schemas.lens.dev/open-actions/1.0.0.json"}
